Metadata-Version: 2.1
Name: MemoryCasheDataBase-Client
Version: 0.0.1
Summary: Python client for MemoryCasheDataBase_Server database and key-value store
Home-page: https://github.com/ma-karov/MemoryCasheDataBase_Client/
Author: Никита Макаров, Мария Кутыркина
Author-email: ma-kar-ov@yandex.ru, mariahkutyrkina@yandex.ru
License: Apache License, Version 2.0, see LICENSE file
Download-URL: https://github.com/ma-karov/MemoryCasheDataBase_Client/archive/refs/tags/0.0.1.zip
Platform: UNKNOWN
Classifier: Programming Language :: Python
Classifier: Programming Language :: Python :: 3
Classifier: Programming Language :: Python :: 3.0
Classifier: Programming Language :: Python :: 3.1
Classifier: Programming Language :: Python :: 3.2
Classifier: Programming Language :: Python :: 3.3
Classifier: Programming Language :: Python :: 3.4
Classifier: Programming Language :: Python :: 3.5
Classifier: Programming Language :: Python :: 3.6
Classifier: Programming Language :: Python :: 3.7
Classifier: Programming Language :: Python :: 3.8
Classifier: Programming Language :: Python :: 3.9
Classifier: Programming Language :: Python :: 3.10
Classifier: Programming Language :: Python :: 3.11
Classifier: Programming Language :: Python :: 3.12
Classifier: Programming Language :: Python :: 3.13
Classifier: Programming Language :: Python :: 3.14
Classifier: Programming Language :: Python :: Implementation :: CPython
Classifier: Programming Language :: Python :: Implementation :: PyPy
